{"version":"12.1","name":"Asymmetric Observer","aircraft_type":0,"era":{"selected":1},"cockpits":{"positions":[{"type":3,"upgrades":[false,false,false,true,false,false],"safety":[false,false,false,false,false,false],"sights":[false,false,false,false],"bombsight":0},{"type":0,"upgrades":[false,false,false,true,false,false],"safety":[false,false,false,false,false,false],"sights":[false,false,false,false],"bombsight":0}]},"passengers":{"seats":0,"beds":0,"connected":false},"engines":{"engines":[{"selected_stats":{"name":"SLW Sigvird 180hp","overspeed":32,"altitude":49,"torque":1,"rumble":0,"oiltank":false,"pulsejet":false,"liftbleed":0,"wetmass":0,"mass":7,"drag":7,"control":0,"cost":11,"reqsections":0,"visibility":0,"flightstress":0,"escape":0,"pitchstab":0,"latstab":0,"cooling":0,"reliability":1,"power":18,"fuelconsumption":22,"maxstrain":0,"structure":0,"pitchboost":0,"pitchspeed":0,"wingarea":0,"toughness":0,"upkeep":0,"crashsafety":0,"bomb_mass":0,"fuel":0,"charge":0},"selected_inputs":{"name":"SLW Sigvird 180hp","engine_type":0,"type":4,"era_sel":1,"displacement":11,"compression":6,"cyl_per_row":4,"rows":1,"RPM_boost":1,"material_fudge":1,"quality_fudge":1.3,"compressor_type":2,"compressor_count":2,"min_IAF":0,"upgrades":[false,false,false,false]},"cooling_count":0,"radiator_index":-1,"selected_mount":7,"use_pushpull":false,"pp_torque_to_struct":false,"use_driveshafts":false,"geared_propeller_ratio":0,"geared_propeller_reliability":0,"cowl_sel":1,"is_generator":false,"has_alternator":true,"intake_fan":false}],"radiators":[],"is_asymmetric":true},"propeller":{"type":1,"upgrade":0},"frames":{"sections":[{"frame":3,"geodesic":true,"monocoque":false,"lifting_body":false,"internal_bracing":false},{"frame":3,"geodesic":true,"monocoque":false,"lifting_body":false,"internal_bracing":false},{"frame":3,"geodesic":true,"monocoque":false,"lifting_body":false,"internal_bracing":false},{"frame":3,"geodesic":true,"monocoque":false,"lifting_body":false,"internal_bracing":false}],"tail_sections":[{"frame":3,"geodesic":true,"monocoque":false,"lifting_body":false,"internal_bracing":false},{"frame":3,"geodesic":true,"monocoque":false,"lifting_body":false,"internal_bracing":false}],"tail_index":2,"use_farman":false,"use_boom":false,"flying_wing":false,"sel_skin":1},"wings":{"wing_list":[{"surface":0,"area":17,"span":8,"anhedral":0,"dihedral":0,"gull":false,"deck":0},{"surface":0,"area":17,"span":8,"gull":false,"dihedral":0,"anhedral":0,"deck":2}],"mini_wing_list":[],"wing_stagger":4,"is_swept":false,"is_closed":false},"stabilizers":{"hstab_sel":0,"hstab_count":1,"vstab_sel":0,"vstab_count":1},"controlsurfaces":{"aileron_sel":0,"rudder_sel":0,"elevator_sel":0,"flaps_sel":1,"slats_sel":0,"drag_sel":[false,false,false]},"reinforcements":{"ext_wood_count":[1,1,0,0,0,0,0,0,0],"ext_steel_count":[0,0,0,0,0,0,0,0,0],"cant_count":[0,0,0,0,0],"wires":true,"cabane_sel":1,"wing_blades":false},"fuel":{"tank_count":[2,0,0,0],"self_sealing":false,"fire_extinguisher":false},"munitions":{"bomb_count":0,"rocket_count":0,"bay_count":0,"bay1":false,"bay2":false},"cargo":{"space_sel":0},"gear":{"gear_sel":2,"retract":false,"extra_sel":[false,false,true]},"accessories":{"v":2,"armour_coverage":[0,0,0,0,0,0,0,0],"electrical_count":[0,1,0],"radio_sel":1,"recon_sel":[0,0,0,0,0,0,1],"visi_sel":[false,false,true],"clim_sel":[false,false,false],"auto_sel":1,"cont_sel":0},"optimization":{"free_dots":0,"cost":0,"bleed":1,"escape":0,"mass":0,"toughness":-1,"maxstrain":0,"reliability":0,"drag":0},"weapons":{"weapon_systems":[{"weapon_type":3,"fixed":false,"directions":[true,false,false,true,false,false],"weapons":[{"fixed":false,"wing":false,"covered":false,"accessible":false,"free_accessible":true,"synchronization":-1,"w_count":1}],"ammo":1,"action":0,"projectile":0,"repeating":false,"seat":0},{"weapon_type":2,"fixed":false,"directions":[false,true,true,false,true,true],"weapons":[{"fixed":false,"wing":false,"covered":false,"accessible":true,"free_accessible":false,"synchronization":-1,"w_count":1}],"ammo":3,"action":2,"projectile":0,"repeating":true,"seat":1}],"brace_count":0},"used":{"enabled":false,"burnt_out":0,"ragged":0,"hefty":0,"sticky_guns":0,"weak":0,"fragile":0,"leaky":0,"sluggish":0},"rotor":{"type":0,"rotor_count":0,"rotor_span":0,"rotor_mat":0,"is_tandem":false,"accessory":false,"blade_idx":0}}